[
  {
    "id": 5000,
    "name": "Veg Spring Roll",
    "description": "Veg Spring Roll - delicious and freshly made.",
    "price": 389,
    "veg": true,
    "image": "/src/assets/items/veg_spring_roll.jpeg",
    "rating": 4.3,
    "category": "Appetizer",
    "dishType": "Sandwiches",
    "mealTime": "Breakfast",
    "trending": false
  },
  {
    "id": 5001,
    "name": "Chicken Dumplings",
    "description": "Chicken Dumplings - delicious and freshly made.",
    "price": 125,
    "veg": false,
    "image": "/src/assets/items/chicken_dumplings.jpeg",
    "rating": 4.4,
    "category": "Appetizer",
    "dishType": "Sandwiches",
    "mealTime": "Breakfast",
    "trending": true
  },
  {
    "id": 5002,
    "name": "Chocolate Cake",
    "description": "Chocolate Cake - delicious and freshly made.",
    "price": 385,
    "veg": true,
    "image": "/src/assets/items/chocolate_cake.jpeg",
    "rating": 4.6,
    "category": "Main Course",
    "dishType": "Drinks",
    "mealTime": "Breakfast",
    "trending": true
  },
  {
    "id": 5003,
    "name": "Gulab Jamun",
    "description": "Gulab Jamun - delicious and freshly made.",
    "price": 147,
    "veg": true,
    "image": "/src/assets/items/gulab_jamun.jpeg",
    "rating": 4.7,
    "category": "Appetizer",
    "dishType": "Pizza",
    "mealTime": "Breakfast",
    "trending": false
  },
  {
    "id": 5004,
    "name": "Paneer Paratha",
    "description": "Paneer Paratha - delicious and freshly made.",
    "price": 277,
    "veg": true,
    "image": "/src/assets/items/paneer_paratha.jpeg",
    "rating": 4.6,
    "category": "Dessert",
    "dishType": "Parathas",
    "mealTime": "Dinner",
    "trending": false
  },
  {
    "id": 5005,
    "name": "Seekh Kebab",
    "description": "Seekh Kebab - delicious and freshly made.",
    "price": 106,
    "veg": false,
    "image": "/src/assets/items/seekh_kebab.jpeg",
    "rating": 5.0,
    "category": "Appetizer",
    "dishType": "Cakes",
    "mealTime": "Lunch",
    "trending": true
  },
  {
    "id": 5006,
    "name": "Mango Smoothie",
    "description": "Mango Smoothie - delicious and freshly made.",
    "price": 264,
    "veg": true,
    "image": "/src/assets/items/mango_smoothie.jpeg",
    "rating": 4.0,
    "category": "Appetizer",
    "dishType": "Pizza",
    "mealTime": "Breakfast",
    "trending": false
  },
  {
    "id": 5007,
    "name": "Garlic Naan",
    "description": "Garlic Naan - delicious and freshly made.",
    "price": 136,
    "veg": true,
    "image": "/src/assets/items/garlic_naan.jpeg",
    "rating": 4.5,
    "category": "Appetizer",
    "dishType": "Desserts",
    "mealTime": "Lunch",
    "trending": true
  },
  {
    "id": 5008,
    "name": "Greek Salad",
    "description": "Greek Salad - delicious and freshly made.",
    "price": 167,
    "veg": true,
    "image": "/src/assets/items/greek_salad.jpeg",
    "rating": 4.5,
    "category": "Appetizer",
    "dishType": "Cakes",
    "mealTime": "Breakfast",
    "trending": false
  },
  {
    "id": 5009,
    "name": "Veggie Burger",
    "description": "Veggie Burger - delicious and freshly made.",
    "price": 234,
    "veg": true,
    "image": "/src/assets/items/veggie_burger.jpeg",
    "rating": 4.7,
    "category": "Beverage",
    "dishType": "Cakes",
    "mealTime": "Dinner",
    "trending": true
  },
  {
    "id": 5010,
    "name": "Club Sandwich",
    "description": "Club Sandwich - delicious and freshly made.",
    "price": 353,
    "veg": false,
    "image": "/src/assets/items/club_sandwich.jpeg",
    "rating": 4.9,
    "category": "Dessert",
    "dishType": "Kebabs",
    "mealTime": "Breakfast",
    "trending": false
  },
  {
    "id": 5011,
    "name": "Margherita Pizza",
    "description": "Margherita Pizza - delicious and freshly made.",
    "price": 196,
    "veg": false,
    "image": "/src/assets/items/margherita_pizza.jpeg",
    "rating": 4.8,
    "category": "Main Course",
    "dishType": "Sandwiches",
    "mealTime": "Dinner",
    "trending": true
  },
  {
    "id": 5012,
    "name": "Pepperoni Pizza",
    "description": "Pepperoni Pizza - delicious and freshly made.",
    "price": 221,
    "veg": false,
    "image": "/src/assets/items/pepperoni_pizza.jpeg",
    "rating": 4.4,
    "category": "Appetizer",
    "dishType": "Burgers",
    "mealTime": "Lunch",
    "trending": true
  },
  {
    "id": 5013,
    "name": "Black Forest Cake",
    "description": "Black Forest Cake - delicious and freshly made.",
    "price": 210,
    "veg": true,
    "image": "/src/assets/items/black_forest_cake.jpeg",
    "rating": 4.1,
    "category": "Appetizer",
    "dishType": "Kebabs",
    "mealTime": "Lunch",
    "trending": false
  },
  {
    "id": 5014,
    "name": "Rasgulla",
    "description": "Rasgulla - delicious and freshly made.",
    "price": 348,
    "veg": false,
    "image": "/src/assets/items/rasgulla.jpeg",
    "rating": 4.1,
    "category": "Beverage",
    "dishType": "Parathas",
    "mealTime": "Lunch",
    "trending": true
  },
  {
    "id": 5015,
    "name": "Aloo Paratha",
    "description": "Aloo Paratha - delicious and freshly made.",
    "price": 388,
    "veg": true,
    "image": "/src/assets/items/aloo_paratha.jpeg",
    "rating": 4.6,
    "category": "Beverage",
    "dishType": "Drinks",
    "mealTime": "Dinner",
    "trending": true
  },
  {
    "id": 5016,
    "name": "Chicken Tikka",
    "description": "Chicken Tikka - delicious and freshly made.",
    "price": 306,
    "veg": false,
    "image": "/src/assets/items/chicken_tikka.jpeg",
    "rating": 4.7,
    "category": "Main Course",
    "dishType": "Kebabs",
    "mealTime": "Breakfast",
    "trending": false
  },
  {
    "id": 5017,
    "name": "Cold Coffee",
    "description": "Cold Coffee - delicious and freshly made.",
    "price": 201,
    "veg": false,
    "image": "/src/assets/items/cold_coffee.jpeg",
    "rating": 4.4,
    "category": "Beverage",
    "dishType": "Chinese",
    "mealTime": "Lunch",
    "trending": true
  },
  {
    "id": 5018,
    "name": "Butter Naan",
    "description": "Butter Naan - delicious and freshly made.",
    "price": 262,
    "veg": true,
    "image": "/src/assets/items/butter_naan.jpeg",
    "rating": 4.1,
    "category": "Main Course",
    "dishType": "Breads",
    "mealTime": "Breakfast",
    "trending": false
  },
  {
    "id": 5019,
    "name": "Caesar Salad",
    "description": "Caesar Salad - delicious and freshly made.",
    "price": 164,
    "veg": true,
    "image": "/src/assets/items/caesar_salad.jpeg",
    "rating": 4.1,
    "category": "Appetizer",
    "dishType": "Pizza",
    "mealTime": "Lunch",
    "trending": true
  },
  {
    "id": 5020,
    "name": "Cheese Burger",
    "description": "Cheese Burger - delicious and freshly made.",
    "price": 140,
    "veg": false,
    "image": "/src/assets/items/cheese_burger.jpeg",
    "rating": 4.0,
    "category": "Appetizer",
    "dishType": "Burgers",
    "mealTime": "Dinner",
    "trending": false
  },
  {
    "id": 5021,
    "name": "Chicken Sandwich",
    "description": "Chicken Sandwich - delicious and freshly made.",
    "price": 365,
    "veg": false,
    "image": "/src/assets/items/chicken_sandwich.jpeg",
    "rating": 4.5,
    "category": "Appetizer",
    "dishType": "Pizza",
    "mealTime": "Breakfast",
    "trending": true
  },
  {
    "id": 5022,
    "name": "Farmhouse Pizza",
    "description": "Farmhouse Pizza - delicious and freshly made.",
    "price": 246,
    "veg": false,
    "image": "/src/assets/items/farmhouse_pizza.jpeg",
    "rating": 4.2,
    "category": "Main Course",
    "dishType": "Burgers",
    "mealTime": "Dinner",
    "trending": false
  },
  {
    "id": 5023,
    "name": "Choco Lava Cake",
    "description": "Choco Lava Cake - delicious and freshly made.",
    "price": 320,
    "veg": true,
    "image": "/src/assets/items/cake.jpeg",
    "rating": 4.2,
    "category": "Dessert",
    "dishType": "Chinese",
    "mealTime": "Dinner",
    "trending": true
  },
  {
    "id": 5024,
    "name": "Jalebi",
    "description": "Jalebi - delicious and freshly made.",
    "price": 124,
    "veg": false,
    "image": "/src/assets/items/jalebi.jpeg",
    "rating": 4.7,
    "category": "Dessert",
    "dishType": "Salads",
    "mealTime": "Dinner",
    "trending": true
  },
  {
    "id": 5025,
    "name": "Onion Paratha",
    "description": "Onion Paratha - delicious and freshly made.",
    "price": 267,
    "veg": true,
    "image": "/src/assets/items/onion_paratha.jpeg",
    "rating": 5.0,
    "category": "Main Course",
    "dishType": "Desserts",
    "mealTime": "Lunch",
    "trending": true
  },
  {
    "id": 5026,
    "name": "Mutton Kebab",
    "description": "Mutton Kebab - delicious and freshly made.",
    "price": 395,
    "veg": false,
    "image": "/src/assets/items/mutton_kebab.jpeg",
    "rating": 4.8,
    "category": "Main Course",
    "dishType": "Salads",
    "mealTime": "Lunch",
    "trending": true
  },
  {
    "id": 5027,
    "name": "Lassi",
    "description": "Lassi - delicious and freshly made.",
    "price": 332,
    "veg": true,
    "image": "/src/assets/items/lassi.jpeg",
    "rating": 4.2,
    "category": "Dessert",
    "dishType": "Parathas",
    "mealTime": "Lunch",
    "trending": false
  },
  {
    "id": 5028,
    "name": "Tandoori Roti",
    "description": "Tandoori Roti - delicious and freshly made.",
    "price": 128,
    "veg": false,
    "image": "/src/assets/items/tandoori_roti.jpeg",
    "rating": 4.1,
    "category": "Main Course",
    "dishType": "Pizza",
    "mealTime": "Dinner",
    "trending": true
  },
  {
    "id": 5029,
    "name": "Sprouts Salad",
    "description": "Sprouts Salad - delicious and freshly made.",
    "price": 273,
    "veg": true,
    "image": "/src/assets/items/sprouts_salad.jpeg",
    "rating": 4.7,
    "category": "Dessert",
    "dishType": "Parathas",
    "mealTime": "Lunch",
    "trending": false
  },
  {
    "id": 5030,
    "name": "Paneer Burger",
    "description": "Paneer Burger - delicious and freshly made.",
    "price": 242,
    "veg": true,
    "image": "/src/assets/items/paneer_burger.jpeg",
    "rating": 4.7,
    "category": "Appetizer",
    "dishType": "Chinese",
    "mealTime": "Lunch",
    "trending": false
  },
  {
    "id": 5031,
    "name": "Egg Sandwich",
    "description": "Egg Sandwich - delicious and freshly made.",
    "price": 101,
    "veg": false,
    "image": "/src/assets/items/egg_sandwich.jpeg",
    "rating": 4.7,
    "category": "Dessert",
    "dishType": "Burgers",
    "mealTime": "Breakfast",
    "trending": false
  },
  {
    "id": 5032,
    "name": "Veg Pizza",
    "description": "Veg Pizza - delicious and freshly made.",
    "price": 311,
    "veg": true,
    "image": "/src/assets/items/veg_pizza.jpeg",
    "rating": 4.8,
    "category": "Appetizer",
    "dishType": "Parathas",
    "mealTime": "Lunch",
    "trending": false
  },
  {
    "id": 5033,
    "name": "Strawberry Cake",
    "description": "Strawberry Cake - delicious and freshly made.",
    "price": 198,
    "veg": true,
    "image": "/src/assets/items/strawberry_cake.jpeg",
    "rating": 4.3,
    "category": "Appetizer",
    "dishType": "Parathas",
    "mealTime": "Breakfast",
    "trending": false
  },
  {
    "id": 5034,
    "name": "Kheer",
    "description": "Kheer - delicious and freshly made.",
    "price": 289,
    "veg": false,
    "image": "/src/assets/items/kheer.jpeg",
    "rating": 4.2,
    "category": "Dessert",
    "dishType": "Salads",
    "mealTime": "Lunch",
    "trending": false
  },
  {
    "id": 5035,
    "name": "Gobi Paratha",
    "description": "Gobi Paratha - delicious and freshly made.",
    "price": 252,
    "veg": true,
    "image": "/src/assets/items/gobi_paratha.jpeg",
    "rating": 4.3,
    "category": "Appetizer",
    "dishType": "Drinks",
    "mealTime": "Dinner",
    "trending": false
  },
  {
    "id": 5036,
    "name": "Chicken Seekh",
    "description": "Chicken Seekh - delicious and freshly made.",
    "price": 135,
    "veg": false,
    "image": "/src/assets/items/chicken_seekh.jpeg",
    "rating": 4.1,
    "category": "Dessert",
    "dishType": "Parathas",
    "mealTime": "Lunch",
    "trending": false
  },
  {
    "id": 5037,
    "name": "Orange Juice",
    "description": "Orange Juice - delicious and freshly made.",
    "price": 127,
    "veg": false,
    "image": "/src/assets/items/orange_juice.jpeg",
    "rating": 4.5,
    "category": "Appetizer",
    "dishType": "Breads",
    "mealTime": "Dinner",
    "trending": false
  },
  {
    "id": 5038,
    "name": "Missi Roti",
    "description": "Missi Roti - delicious and freshly made.",
    "price": 225,
    "veg": false,
    "image": "/src/assets/items/missi_roti.jpeg",
    "rating": 4.7,
    "category": "Appetizer",
    "dishType": "Salads",
    "mealTime": "Breakfast",
    "trending": false
  },
  {
    "id": 5039,
    "name": "Russian Salad",
    "description": "Russian Salad - delicious and freshly made.",
    "price": 230,
    "veg": true,
    "image": "/src/assets/items/russian_salad.jpeg",
    "rating": 4.0,
    "category": "Dessert",
    "dishType": "Desserts",
    "mealTime": "Breakfast",
    "trending": false
  },
  {
    "id": 5040,
    "name": "Beetroot Burger",
    "description": "Beetroot Burger - delicious and freshly made.",
    "price": 158,
    "veg": false,
    "image": "/src/assets/items/beetroot_burger.jpeg",
    "rating": 4.8,
    "category": "Beverage",
    "dishType": "Salads",
    "mealTime": "Breakfast",
    "trending": false
  },
  {
    "id": 5041,
    "name": "Tuna Sandwich",
    "description": "Tuna Sandwich - delicious and freshly made.",
    "price": 315,
    "veg": false,
    "image": "/src/assets/items/tuna_sandwich.jpeg",
    "rating": 4.4,
    "category": "Dessert",
    "dishType": "Cakes",
    "mealTime": "Dinner",
    "trending": false
  },
  {
    "id": 5042,
    "name": "Mexican Pizza",
    "description": "Mexican Pizza - delicious and freshly made.",
    "price": 309,
    "veg": false,
    "image": "/src/assets/items/mexican_pizza.jpeg",
    "rating": 4.8,
    "category": "Dessert",
    "dishType": "Parathas",
    "mealTime": "Dinner",
    "trending": true
  },
  {
    "id": 5043,
    "name": "Pineapple Pastry",
    "description": "Pineapple Pastry - delicious and freshly made.",
    "price": 138,
    "veg": false,
    "image": "/src/assets/items/pineapple_pastry.jpeg",
    "rating": 4.2,
    "category": "Dessert",
    "dishType": "Parathas",
    "mealTime": "Lunch",
    "trending": true
  },
  {
    "id": 5044,
    "name": "Basundi",
    "description": "Basundi - delicious and freshly made.",
    "price": 97,
    "veg": false,
    "image": "/src/assets/items/basundi.jpeg",
    "rating": 4.5,
    "category": "Main Course",
    "dishType": "Salads",
    "mealTime": "Dinner",
    "trending": true
  },
  {
    "id": 5045,
    "name": "Methi Paratha",
    "description": "Methi Paratha - delicious and freshly made.",
    "price": 398,
    "veg": true,
    "image": "/src/assets/items/methi_paratha.jpeg",
    "rating": 4.8,
    "category": "Beverage",
    "dishType": "Salads",
    "mealTime": "Lunch",
    "trending": true
  },
  {
    "id": 5046,
    "name": "Hariyali Kebab",
    "description": "Hariyali Kebab - delicious and freshly made.",
    "price": 400,
    "veg": false,
    "image": "/src/assets/items/hariyali_kebab.jpeg",
    "rating": 4.5,
    "category": "Dessert",
    "dishType": "Cakes",
    "mealTime": "Dinner",
    "trending": false
  },
  {
    "id": 5047,
    "name": "Masala Chai",
    "description": "Masala Chai - delicious and freshly made.",
    "price": 297,
    "veg": false,
    "image": "/src/assets/items/masala_chai.jpeg",
    "rating": 4.4,
    "category": "Beverage",
    "dishType": "Desserts",
    "mealTime": "Lunch",
    "trending": false
  },
  {
    "id": 5048,
    "name": "Roomali Roti",
    "description": "Roomali Roti - delicious and freshly made.",
    "price": 130,
    "veg": false,
    "image": "/src/assets/items/roomali_roti.jpeg",
    "rating": 4.2,
    "category": "Dessert",
    "dishType": "Breads",
    "mealTime": "Breakfast",
    "trending": true
  },
  {
    "id": 5049,
    "name": "Corn Salad",
    "description": "Corn Salad - delicious and freshly made.",
    "price": 97,
    "veg": true,
    "image": "/src/assets/items/corn_salad.jpeg",
    "rating": 4.2,
    "category": "Dessert",
    "dishType": "Chinese",
    "mealTime": "Dinner",
    "trending": true
  },
  {
    "id": 5050,
    "name": "Aloo Tikki Burger",
    "description": "Aloo Tikki Burger - delicious and freshly made.",
    "price": 150,
    "veg": true,
    "image": "/src/assets/items/aloo_tikki_burger.jpeg",
    "rating": 4.7,
    "category": "Beverage",
    "dishType": "Cakes",
    "mealTime": "Lunch",
    "trending": false
  },
  {
    "id": 5051,
    "name": "Grilled Cheese Sandwich",
    "description": "Grilled Cheese Sandwich - delicious and freshly made.",
    "price": 387,
    "veg": false,
    "image": "/src/assets/items/grilled_cheese_sandwich.jpeg",
    "rating": 4.7,
    "category": "Dessert",
    "dishType": "Salads",
    "mealTime": "Lunch",
    "trending": true
  },
  {
    "id": 5052,
    "name": "Cheese Burst Pizza",
    "description": "Cheese Burst Pizza - delicious and freshly made.",
    "price": 286,
    "veg": false,
    "image": "/src/assets/items/cheese_burst_pizza.jpeg",
    "rating": 4.5,
    "category": "Appetizer",
    "dishType": "Cakes",
    "mealTime": "Breakfast",
    "trending": true
  },
  {
    "id": 5053,
    "name": "Red Velvet Cake",
    "description": "Red Velvet Cake - delicious and freshly made.",
    "price": 248,
    "veg": true,
    "image": "/src/assets/items/red_velvet_cake.jpeg",
    "rating": 4.9,
    "category": "Main Course",
    "dishType": "Chinese",
    "mealTime": "Lunch",
    "trending": true
  },
  {
    "id": 5054,
    "name": "Sandesh",
    "description": "Sandesh - delicious and freshly made.",
    "price": 183,
    "veg": false,
    "image": "/src/assets/items/sandesh.jpeg",
    "rating": 4.4,
    "category": "Dessert",
    "dishType": "Salads",
    "mealTime": "Lunch",
    "trending": true
  },
  {
    "id": 5055,
    "name": "Paneer Kulcha",
    "description": "Paneer Kulcha - delicious and freshly made.",
    "price": 276,
    "veg": true,
    "image": "/src/assets/items/paneer_kulcha.jpeg",
    "rating": 4.5,
    "category": "Main Course",
    "dishType": "Kebabs",
    "mealTime": "Lunch",
    "trending": false
  },
  {
    "id": 5056,
    "name": "Galouti Kebab",
    "description": "Galouti Kebab - delicious and freshly made.",
    "price": 172,
    "veg": false,
    "image": "/src/assets/items/galouti_kebab.jpeg",
    "rating": 4.6,
    "category": "Main Course",
    "dishType": "Breads",
    "mealTime": "Lunch",
    "trending": false
  },
  {
    "id": 5057,
    "name": "Green Tea",
    "description": "Green Tea - delicious and freshly made.",
    "price": 272,
    "veg": true,
    "image": "/src/assets/items/green_tea.jpeg",
    "rating": 4.4,
    "category": "Appetizer",
    "dishType": "Drinks",
    "mealTime": "Lunch",
    "trending": true
  },
  {
    "id": 5058,
    "name": "Lachha Paratha",
    "description": "Lachha Paratha - delicious and freshly made.",
    "price": 120,
    "veg": true,
    "image": "/src/assets/items/lachha_paratha.jpeg",
    "rating": 4.7,
    "category": "Appetizer",
    "dishType": "Drinks",
    "mealTime": "Lunch",
    "trending": false
  },
  {
    "id": 5059,
    "name": "Fruit Salad",
    "description": "Fruit Salad - delicious and freshly made.",
    "price": 297,
    "veg": true,
    "image": "/src/assets/items/fruit_salad.jpeg",
    "rating": 4.2,
    "category": "Dessert",
    "dishType": "Burgers",
    "mealTime": "Lunch",
    "trending": false
  }
]